cn_trader/__init__.py
cn_trader/ui.py
cn_trader/stock/__init__.py
cn_trader/stock/constant.py
cn_trader/stock/mainland.py
cn_trader/stock/util.py
cn_trader/stock/indicator/__init__.py
cn_trader/stock/indicator/ene.py
cn_trader/stock/observer/__init__.py
cn_trader/stock/observer/buysell.py
cn_trader/stock/observer/trades.py
cn_trader/stock/strategy/__init__.py
cn_trader/stock/strategy/base.py
cn_trader/stock/strategy/ene.py
cn_trader/stock/strategy/sma.py
tests/__init__.py
tests/base.py
tests/test_stock_mainland.py
tests/test_util.py
cn_trader-1.0.2.dist-info/LICENSE
cn_trader-1.0.2.dist-info/METADATA
cn_trader-1.0.2.dist-info/WHEEL
cn_trader-1.0.2.dist-info/entry_points.txt
cn_trader-1.0.2.dist-info/top_level.txt
cn_trader-1.0.2.dist-info/RECORD
