Metadata-Version: 2.1
Name: cn-trader
Version: 1.0.2
Summary: Back testing system for China market
Home-page: https://github.com/codfish-zz/cn-trader
Author: BigFish
Author-email: huui1998@163.com
License: Apache-2.0
Keywords: trading,development
Platform: any
Classifier: Development Status :: 5 - Production/Stable
Classifier: Intended Audience :: Developers
Classifier: Intended Audience :: Financial and Insurance Industry
Classifier: Topic :: Software Development
Classifier: Topic :: Office/Business :: Financial
Classifier: License :: OSI Approved :: Apache Software License
Classifier: Programming Language :: Python :: 3
Classifier: Programming Language :: Python :: 3.2
Classifier: Programming Language :: Python :: 3.3
Classifier: Programming Language :: Python :: 3.4
Classifier: Programming Language :: Python :: 3.5
Classifier: Programming Language :: Python :: 3.6
Classifier: Programming Language :: Python :: 3.7
Classifier: Programming Language :: Python :: 3.8
Classifier: Programming Language :: Python :: 3.9
Classifier: Programming Language :: Python :: 3.10
Classifier: Programming Language :: Python :: 3.11
Classifier: Operating System :: OS Independent
License-File: LICENSE
Requires-Dist: akshare
Requires-Dist: backtrader
Requires-Dist: matplotlib
Requires-Dist: prompt-toolkit
Requires-Dist: rich
